cveda/__init__.py
cveda/annotations.py
cveda/api.py
cveda/cli.py
cveda/data_io.py
cveda/image_quality.py
cveda/ingest.py
cveda/inspect.py
cveda/schema.py
cveda/segmentation.py
cveda/split_generator.py
cveda/checks/__init__.py
cveda/checks/bbox_sanity.py
cveda/checks/category_consistency.py
cveda/checks/completeness.py
cveda/checks/coverage.py
cveda/checks/hard_negative.py
cveda/checks/overlap.py
cveda/checks/splits.py
cveda/checks/summary.py
cveda/distribution/__init__.py
cveda/distribution/aspect_ratio.py
cveda/distribution/bbox_statistics.py
cveda/distribution/class_distribution.py
cveda/distribution/cooccurrence.py
cveda/distribution/spatial_heatmap.py
cveda/features/absolute_coordinate_patterns.py
cveda/features/annotation_confidence.py
cveda/features/annotation_lifespan_drift.py
cveda/features/annotation_rarity_buckets.py
cveda/features/background_relevance.py
cveda/features/bbox_border_alignment.py
cveda/features/camera_diversity.py
cveda/features/color_cast_detection.py
cveda/features/compression_anomaly.py
cveda/features/containment_detection.py
cveda/features/duplicate_annotation_ids.py
cveda/features/environment_diversity.py
cveda/features/geographic_clustering.py
cveda/features/heirarchy_validation.py
cveda/features/illumination_diversity.py
cveda/features/inter_annotator_disagreement.py
cveda/features/metadata_drift.py
cveda/features/mislabel_candidate_generator.py
cveda/features/multiresolution_similarity.py
cveda/features/mutual_exclusion.py
cveda/features/noise_type_classifier.py
cveda/features/object_alignment_patterns.py
cveda/features/object_distance_distribution.py
cveda/features/objects_touching_edges.py
cveda/features/occlusion_estimator.py
cveda/features/polygon_smoothness.py
cveda/features/pose_diversity.py
cveda/features/random_crop_inspection.py
cveda/features/relative_size_ratios.py
cveda/features/repeated_background_detector.py
cveda/features/repetitive_layouts.py
cveda/features/seasonal_coverage.py
cveda/features/shadow_intensity.py
cveda-0.1.1.dist-info/licenses/LICENSE
cveda-0.1.1.dist-info/METADATA
cveda-0.1.1.dist-info/WHEEL
cveda-0.1.1.dist-info/top_level.txt
cveda-0.1.1.dist-info/RECORD
