Metadata-Version: 2.4
Name: cveda
Version: 0.1.1
Summary: Lightweight EDA utilities for computer vision datasets
Author: Aditya
License: MIT
Requires-Python: >=3.8
License-File: LICENSE
Dynamic: license-file
